Clien/__init__.py
Clien/clien.py
Clien_karjakak-0.1.7.dist-info/METADATA
Clien_karjakak-0.1.7.dist-info/WHEEL
Clien_karjakak-0.1.7.dist-info/entry_points.txt
Clien_karjakak-0.1.7.dist-info/top_level.txt
Clien_karjakak-0.1.7.dist-info/RECORD
